DESCRIPTION
MANIFEST.in
README
README.rst
setup.py
easy_news/__init__.py
easy_news/__init__.pyc
easy_news/admin.py
easy_news/menu.py
easy_news/models.py
easy_news/search_indexes.py
easy_news/settings.py
easy_news/urls.py
easy_news/views.py
easy_news/doc/Makefile
easy_news/doc/build/genindex.html
easy_news/doc/build/index.html
easy_news/doc/build/install.html
easy_news/doc/build/objects.inv
easy_news/doc/build/search.html
easy_news/doc/build/searchindex.js
easy_news/doc/build/usage.html
easy_news/doc/build/.doctrees/environment.pickle
easy_news/doc/build/.doctrees/index.doctree
easy_news/doc/build/.doctrees/install.doctree
easy_news/doc/build/.doctrees/usage.doctree
easy_news/doc/build/_sources/index.txt
easy_news/doc/build/_sources/install.txt
easy_news/doc/build/_sources/usage.txt
easy_news/doc/build/_static/contents.png
easy_news/doc/build/_static/default.css
easy_news/doc/build/_static/doctools.js
easy_news/doc/build/_static/file.png
easy_news/doc/build/_static/jquery.js
easy_news/doc/build/_static/minus.png
easy_news/doc/build/_static/navigation.png
easy_news/doc/build/_static/plus.png
easy_news/doc/build/_static/pygments.css
easy_news/doc/build/_static/rightsidebar.css
easy_news/doc/build/_static/searchtools.js
easy_news/doc/build/_static/sphinxdoc.css
easy_news/doc/build/_static/stickysidebar.css
easy_news/doc/build/_static/traditional.css
easy_news/doc/source/conf.py
easy_news/doc/source/index.txt
easy_news/doc/source/install.txt
easy_news/doc/source/usage.txt
easy_news/locale/ru/LC_MESSAGES/django.mo
easy_news/locale/ru/LC_MESSAGES/django.po
easy_news/migrations/0001_initial.py
easy_news/migrations/0002_auto__chg_field_news_title.py
easy_news/migrations/0003_auto__add_field_news_tags.py
easy_news/migrations/__init__.py
easy_news/redsolution_setup/__init__.py
easy_news/redsolution_setup/admin.py
easy_news/redsolution_setup/make.py
easy_news/redsolution_setup/models.py
easy_news/redsolution_setup/urls.py
easy_news/redsolution_setup/views.py
redsolutioncms.django_easy_news.egg-info/PKG-INFO
redsolutioncms.django_easy_news.egg-info/SOURCES.txt
redsolutioncms.django_easy_news.egg-info/dependency_links.txt
redsolutioncms.django_easy_news.egg-info/entry_points.txt
redsolutioncms.django_easy_news.egg-info/not-zip-safe
redsolutioncms.django_easy_news.egg-info/top_level.txt