Metadata-Version: 1.0
Name: redsolutioncms.django-easy-news
Version: 0.2.4
Summary: News application. Allow to publish news on site. You can show news archive,
Home-page: http://packages.python.org/django-easy-news
Author: Alexander Ivanov
Author-email: alexander.ivanov@redsolution.ru
License: GPLv3
Keywords: django news
Platform: UNKNOWN
Classifier: Development Status :: 3 - Alpha
Classifier: Intended Audience :: Developers
Classifier: License :: OSI Approved :: GNU General Public License (GPL)
Classifier: Framework :: Django
Classifier: Environment :: Web Environment
Classifier: Natural Language :: Russian
Classifier: Natural Language :: English
Classifier: Operating System :: OS Independent
Classifier: Programming Language :: Python
Classifier: Topic :: Internet :: WWW/HTTP :: Dynamic Content :: News/Diary
